Metadata-Version: 1.1
Name: machinepack
Version: 0.2
Summary: Toolkit for Python machinepacks
Home-page: http://python-machine.org
Author: Maciej Kucharz
Author-email: maciej.kucharz@syncano.com
License: MIT
Keywords: machinepack tools packages
Platform: UNKNOWN
Classifier: Development Status :: 3 - Alpha
Classifier: Topic :: Utilities
Classifier: License :: OSI Approved :: MIT License
